{"timestamp": "2026-05-06T00:00:06.481306+00:00", "hostname": "frank-XPS-8960", "gpu_type": "NVIDIA L4", "gpu_count": 1, "cpu_percent": 0.0, "memory_percent": 17.5, "memory_used_mb": 5540.18359375, "memory_total_mb": 31740.1875, "gpu": {"utilization": 0.0, "memory_used_mb": 14.0, "memory_total_mb": 23034.0}}
{"timestamp": "2026-05-06T00:00:07.823484+00:00", "hostname": "frank-XPS-8960", "gpu_type": "NVIDIA L4", "gpu_count": 1, "cpu_percent": 0.1, "memory_percent": 17.5, "memory_used_mb": 5544.3046875, "memory_total_mb": 31740.1875, "gpu": {"utilization": 0.0, "memory_used_mb": 14.0, "memory_total_mb": 23034.0}}
{"timestamp": "2026-05-06T00:00:16.998638+00:00", "hostname": "frank-XPS-8960", "gpu_type": "NVIDIA L4", "gpu_count": 1, "cpu_percent": 0.0, "memory_percent": 17.5, "memory_used_mb": 5539.32421875, "memory_total_mb": 31740.1875, "gpu": {"utilization": 0.0, "memory_used_mb": 14.0, "memory_total_mb": 23034.0}}
{"timestamp": "2026-05-06T00:00:18.340063+00:00", "hostname": "frank-XPS-8960", "gpu_type": "NVIDIA L4", "gpu_count": 1, "cpu_percent": 0.7, "memory_percent": 17.5, "memory_used_mb": 5554.12890625, "memory_total_mb": 31740.1875, "gpu": {"utilization": 0.0, "memory_used_mb": 14.0, "memory_total_mb": 23034.0}}
{"timestamp": "2026-05-06T00:00:27.519403+00:00", "hostname": "frank-XPS-8960", "gpu_type": "NVIDIA L4", "gpu_count": 1, "cpu_percent": 0.2, "memory_percent": 17.5, "memory_used_mb": 5547.5234375, "memory_total_mb": 31740.1875, "gpu": {"utilization": 0.0, "memory_used_mb": 14.0, "memory_total_mb": 23034.0}}
{"timestamp": "2026-05-06T00:00:28.857266+00:00", "hostname": "frank-XPS-8960", "gpu_type": "NVIDIA L4", "gpu_count": 1, "cpu_percent": 0.1, "memory_percent": 17.5, "memory_used_mb": 5552.50390625, "memory_total_mb": 31740.1875, "gpu": {"utilization": 0.0, "memory_used_mb": 14.0, "memory_total_mb": 23034.0}}
{"timestamp": "2026-05-06T00:00:38.037212+00:00", "hostname": "frank-XPS-8960", "gpu_type": "NVIDIA L4", "gpu_count": 1, "cpu_percent": 0.0, "memory_percent": 17.5, "memory_used_mb": 5555.54296875, "memory_total_mb": 31740.1875, "gpu": {"utilization": 0.0, "memory_used_mb": 14.0, "memory_total_mb": 23034.0}}
{"timestamp": "2026-05-06T00:00:39.374311+00:00", "hostname": "frank-XPS-8960", "gpu_type": "NVIDIA L4", "gpu_count": 1, "cpu_percent": 0.1, "memory_percent": 17.5, "memory_used_mb": 5547.7578125, "memory_total_mb": 31740.1875, "gpu": {"utilization": 0.0, "memory_used_mb": 14.0, "memory_total_mb": 23034.0}}
{"timestamp": "2026-05-06T00:00:48.554788+00:00", "hostname": "frank-XPS-8960", "gpu_type": "NVIDIA L4", "gpu_count": 1, "cpu_percent": 0.1, "memory_percent": 17.5, "memory_used_mb": 5568.40234375, "memory_total_mb": 31740.1875, "gpu": {"utilization": 0.0, "memory_used_mb": 14.0, "memory_total_mb": 23034.0}}
{"timestamp": "2026-05-06T00:00:49.891422+00:00", "hostname": "frank-XPS-8960", "gpu_type": "NVIDIA L4", "gpu_count": 1, "cpu_percent": 0.1, "memory_percent": 17.6, "memory_used_mb": 5580.4453125, "memory_total_mb": 31740.1875, "gpu": {"utilization": 0.0, "memory_used_mb": 14.0, "memory_total_mb": 23034.0}}
{"timestamp": "2026-05-06T00:00:59.072321+00:00", "hostname": "frank-XPS-8960", "gpu_type": "NVIDIA L4", "gpu_count": 1, "cpu_percent": 0.1, "memory_percent": 17.6, "memory_used_mb": 5585.578125, "memory_total_mb": 31740.1875, "gpu": {"utilization": 0.0, "memory_used_mb": 14.0, "memory_total_mb": 23034.0}}
{"timestamp": "2026-05-06T00:01:00.408157+00:00", "hostname": "frank-XPS-8960", "gpu_type": "NVIDIA L4", "gpu_count": 1, "cpu_percent": 0.1, "memory_percent": 17.6, "memory_used_mb": 5580.10546875, "memory_total_mb": 31740.1875, "gpu": {"utilization": 0.0, "memory_used_mb": 14.0, "memory_total_mb": 23034.0}}
{"timestamp": "2026-05-06T00:01:09.589202+00:00", "hostname": "frank-XPS-8960", "gpu_type": "NVIDIA L4", "gpu_count": 1, "cpu_percent": 0.1, "memory_percent": 17.5, "memory_used_mb": 5545.125, "memory_total_mb": 31740.1875, "gpu": {"utilization": 0.0, "memory_used_mb": 14.0, "memory_total_mb": 23034.0}}
{"timestamp": "2026-05-06T00:01:10.925193+00:00", "hostname": "frank-XPS-8960", "gpu_type": "NVIDIA L4", "gpu_count": 1, "cpu_percent": 0.2, "memory_percent": 17.5, "memory_used_mb": 5555.23046875, "memory_total_mb": 31740.1875, "gpu": {"utilization": 0.0, "memory_used_mb": 14.0, "memory_total_mb": 23034.0}}
{"timestamp": "2026-05-06T00:01:20.107006+00:00", "hostname": "frank-XPS-8960", "gpu_type": "NVIDIA L4", "gpu_count": 1, "cpu_percent": 0.0, "memory_percent": 17.5, "memory_used_mb": 5546.77734375, "memory_total_mb": 31740.1875, "gpu": {"utilization": 0.0, "memory_used_mb": 14.0, "memory_total_mb": 23034.0}}
{"timestamp": "2026-05-06T00:01:21.441865+00:00", "hostname": "frank-XPS-8960", "gpu_type": "NVIDIA L4", "gpu_count": 1, "cpu_percent": 0.1, "memory_percent": 17.5, "memory_used_mb": 5547.15625, "memory_total_mb": 31740.1875, "gpu": {"utilization": 0.0, "memory_used_mb": 14.0, "memory_total_mb": 23034.0}}
{"timestamp": "2026-05-06T00:01:30.623974+00:00", "hostname": "frank-XPS-8960", "gpu_type": "NVIDIA L4", "gpu_count": 1, "cpu_percent": 0.1, "memory_percent": 17.5, "memory_used_mb": 5546.15625, "memory_total_mb": 31740.1875, "gpu": {"utilization": 0.0, "memory_used_mb": 14.0, "memory_total_mb": 23034.0}}
{"timestamp": "2026-05-06T00:01:31.959382+00:00", "hostname": "frank-XPS-8960", "gpu_type": "NVIDIA L4", "gpu_count": 1, "cpu_percent": 0.3, "memory_percent": 17.5, "memory_used_mb": 5550.60546875, "memory_total_mb": 31740.1875, "gpu": {"utilization": 0.0, "memory_used_mb": 14.0, "memory_total_mb": 23034.0}}
{"timestamp": "2026-05-06T00:01:41.141852+00:00", "hostname": "frank-XPS-8960", "gpu_type": "NVIDIA L4", "gpu_count": 1, "cpu_percent": 0.1, "memory_percent": 17.5, "memory_used_mb": 5548.42578125, "memory_total_mb": 31740.1875, "gpu": {"utilization": 0.0, "memory_used_mb": 14.0, "memory_total_mb": 23034.0}}
{"timestamp": "2026-05-06T00:01:42.479625+00:00", "hostname": "frank-XPS-8960", "gpu_type": "NVIDIA L4", "gpu_count": 1, "cpu_percent": 0.1, "memory_percent": 17.5, "memory_used_mb": 5546.44140625, "memory_total_mb": 31740.1875, "gpu": {"utilization": 0.0, "memory_used_mb": 14.0, "memory_total_mb": 23034.0}}
{"timestamp": "2026-05-06T00:01:51.658883+00:00", "hostname": "frank-XPS-8960", "gpu_type": "NVIDIA L4", "gpu_count": 1, "cpu_percent": 0.1, "memory_percent": 17.5, "memory_used_mb": 5544.3828125, "memory_total_mb": 31740.1875, "gpu": {"utilization": 0.0, "memory_used_mb": 14.0, "memory_total_mb": 23034.0}}
{"timestamp": "2026-05-06T00:01:53.000192+00:00", "hostname": "frank-XPS-8960", "gpu_type": "NVIDIA L4", "gpu_count": 1, "cpu_percent": 0.2, "memory_percent": 17.5, "memory_used_mb": 5545.13671875, "memory_total_mb": 31740.1875, "gpu": {"utilization": 0.0, "memory_used_mb": 14.0, "memory_total_mb": 23034.0}}
{"timestamp": "2026-05-06T00:02:02.175561+00:00", "hostname": "frank-XPS-8960", "gpu_type": "NVIDIA L4", "gpu_count": 1, "cpu_percent": 0.3, "memory_percent": 17.4, "memory_used_mb": 5532.984375, "memory_total_mb": 31740.1875, "gpu": {"utilization": 0.0, "memory_used_mb": 14.0, "memory_total_mb": 23034.0}}
{"timestamp": "2026-05-06T00:02:03.517862+00:00", "hostname": "frank-XPS-8960", "gpu_type": "NVIDIA L4", "gpu_count": 1, "cpu_percent": 0.0, "memory_percent": 17.4, "memory_used_mb": 5535.640625, "memory_total_mb": 31740.1875, "gpu": {"utilization": 0.0, "memory_used_mb": 14.0, "memory_total_mb": 23034.0}}
{"timestamp": "2026-05-06T00:02:12.692466+00:00", "hostname": "frank-XPS-8960", "gpu_type": "NVIDIA L4", "gpu_count": 1, "cpu_percent": 0.0, "memory_percent": 17.4, "memory_used_mb": 5538.6015625, "memory_total_mb": 31740.1875, "gpu": {"utilization": 0.0, "memory_used_mb": 14.0, "memory_total_mb": 23034.0}}
{"timestamp": "2026-05-06T00:02:14.035003+00:00", "hostname": "frank-XPS-8960", "gpu_type": "NVIDIA L4", "gpu_count": 1, "cpu_percent": 0.3, "memory_percent": 17.5, "memory_used_mb": 5539.00390625, "memory_total_mb": 31740.1875, "gpu": {"utilization": 0.0, "memory_used_mb": 14.0, "memory_total_mb": 23034.0}}
{"timestamp": "2026-05-06T00:02:23.209567+00:00", "hostname": "frank-XPS-8960", "gpu_type": "NVIDIA L4", "gpu_count": 1, "cpu_percent": 0.1, "memory_percent": 17.5, "memory_used_mb": 5546.01953125, "memory_total_mb": 31740.1875, "gpu": {"utilization": 0.0, "memory_used_mb": 14.0, "memory_total_mb": 23034.0}}
{"timestamp": "2026-05-06T00:02:24.552881+00:00", "hostname": "frank-XPS-8960", "gpu_type": "NVIDIA L4", "gpu_count": 1, "cpu_percent": 0.1, "memory_percent": 17.5, "memory_used_mb": 5551.75390625, "memory_total_mb": 31740.1875, "gpu": {"utilization": 0.0, "memory_used_mb": 14.0, "memory_total_mb": 23034.0}}
{"timestamp": "2026-05-06T00:02:33.726111+00:00", "hostname": "frank-XPS-8960", "gpu_type": "NVIDIA L4", "gpu_count": 1, "cpu_percent": 0.1, "memory_percent": 17.5, "memory_used_mb": 5539.359375, "memory_total_mb": 31740.1875, "gpu": {"utilization": 0.0, "memory_used_mb": 14.0, "memory_total_mb": 23034.0}}
{"timestamp": "2026-05-06T00:02:35.071294+00:00", "hostname": "frank-XPS-8960", "gpu_type": "NVIDIA L4", "gpu_count": 1, "cpu_percent": 0.1, "memory_percent": 17.5, "memory_used_mb": 5549.8984375, "memory_total_mb": 31740.1875, "gpu": {"utilization": 0.0, "memory_used_mb": 14.0, "memory_total_mb": 23034.0}}
{"timestamp": "2026-05-06T00:02:44.243426+00:00", "hostname": "frank-XPS-8960", "gpu_type": "NVIDIA L4", "gpu_count": 1, "cpu_percent": 0.2, "memory_percent": 17.5, "memory_used_mb": 5546.9921875, "memory_total_mb": 31740.1875, "gpu": {"utilization": 0.0, "memory_used_mb": 14.0, "memory_total_mb": 23034.0}}
{"timestamp": "2026-05-06T00:02:45.589024+00:00", "hostname": "frank-XPS-8960", "gpu_type": "NVIDIA L4", "gpu_count": 1, "cpu_percent": 0.2, "memory_percent": 17.5, "memory_used_mb": 5546.3203125, "memory_total_mb": 31740.1875, "gpu": {"utilization": 0.0, "memory_used_mb": 14.0, "memory_total_mb": 23034.0}}
{"timestamp": "2026-05-06T00:02:54.760292+00:00", "hostname": "frank-XPS-8960", "gpu_type": "NVIDIA L4", "gpu_count": 1, "cpu_percent": 0.1, "memory_percent": 17.5, "memory_used_mb": 5548.68359375, "memory_total_mb": 31740.1875, "gpu": {"utilization": 0.0, "memory_used_mb": 14.0, "memory_total_mb": 23034.0}}
{"timestamp": "2026-05-06T00:02:56.108023+00:00", "hostname": "frank-XPS-8960", "gpu_type": "NVIDIA L4", "gpu_count": 1, "cpu_percent": 0.2, "memory_percent": 17.4, "memory_used_mb": 5536.1328125, "memory_total_mb": 31740.1875, "gpu": {"utilization": 0.0, "memory_used_mb": 14.0, "memory_total_mb": 23034.0}}
{"timestamp": "2026-05-06T00:03:05.277071+00:00", "hostname": "frank-XPS-8960", "gpu_type": "NVIDIA L4", "gpu_count": 1, "cpu_percent": 0.2, "memory_percent": 17.5, "memory_used_mb": 5542.47265625, "memory_total_mb": 31740.1875, "gpu": {"utilization": 0.0, "memory_used_mb": 14.0, "memory_total_mb": 23034.0}}
{"timestamp": "2026-05-06T00:03:06.625426+00:00", "hostname": "frank-XPS-8960", "gpu_type": "NVIDIA L4", "gpu_count": 1, "cpu_percent": 0.1, "memory_percent": 17.5, "memory_used_mb": 5548.23046875, "memory_total_mb": 31740.1875, "gpu": {"utilization": 0.0, "memory_used_mb": 14.0, "memory_total_mb": 23034.0}}
{"timestamp": "2026-05-06T00:03:15.793699+00:00", "hostname": "frank-XPS-8960", "gpu_type": "NVIDIA L4", "gpu_count": 1, "cpu_percent": 0.2, "memory_percent": 17.4, "memory_used_mb": 5538.26171875, "memory_total_mb": 31740.1875, "gpu": {"utilization": 0.0, "memory_used_mb": 14.0, "memory_total_mb": 23034.0}}
{"timestamp": "2026-05-06T00:03:17.142153+00:00", "hostname": "frank-XPS-8960", "gpu_type": "NVIDIA L4", "gpu_count": 1, "cpu_percent": 0.1, "memory_percent": 17.5, "memory_used_mb": 5551.13671875, "memory_total_mb": 31740.1875, "gpu": {"utilization": 0.0, "memory_used_mb": 14.0, "memory_total_mb": 23034.0}}
{"timestamp": "2026-05-06T00:03:26.313617+00:00", "hostname": "frank-XPS-8960", "gpu_type": "NVIDIA L4", "gpu_count": 1, "cpu_percent": 0.1, "memory_percent": 17.5, "memory_used_mb": 5542.28515625, "memory_total_mb": 31740.1875, "gpu": {"utilization": 0.0, "memory_used_mb": 14.0, "memory_total_mb": 23034.0}}
{"timestamp": "2026-05-06T00:03:27.659676+00:00", "hostname": "frank-XPS-8960", "gpu_type": "NVIDIA L4", "gpu_count": 1, "cpu_percent": 0.1, "memory_percent": 17.5, "memory_used_mb": 5541.30859375, "memory_total_mb": 31740.1875, "gpu": {"utilization": 0.0, "memory_used_mb": 14.0, "memory_total_mb": 23034.0}}
{"timestamp": "2026-05-06T00:03:36.832999+00:00", "hostname": "frank-XPS-8960", "gpu_type": "NVIDIA L4", "gpu_count": 1, "cpu_percent": 0.1, "memory_percent": 17.4, "memory_used_mb": 5538.01171875, "memory_total_mb": 31740.1875, "gpu": {"utilization": 0.0, "memory_used_mb": 14.0, "memory_total_mb": 23034.0}}
{"timestamp": "2026-05-06T00:03:38.177794+00:00", "hostname": "frank-XPS-8960", "gpu_type": "NVIDIA L4", "gpu_count": 1, "cpu_percent": 0.1, "memory_percent": 17.5, "memory_used_mb": 5545.7421875, "memory_total_mb": 31740.1875, "gpu": {"utilization": 0.0, "memory_used_mb": 14.0, "memory_total_mb": 23034.0}}
{"timestamp": "2026-05-06T00:03:47.353164+00:00", "hostname": "frank-XPS-8960", "gpu_type": "NVIDIA L4", "gpu_count": 1, "cpu_percent": 0.1, "memory_percent": 17.5, "memory_used_mb": 5542.43359375, "memory_total_mb": 31740.1875, "gpu": {"utilization": 0.0, "memory_used_mb": 14.0, "memory_total_mb": 23034.0}}
{"timestamp": "2026-05-06T00:03:48.697545+00:00", "hostname": "frank-XPS-8960", "gpu_type": "NVIDIA L4", "gpu_count": 1, "cpu_percent": 0.4, "memory_percent": 17.5, "memory_used_mb": 5554.28125, "memory_total_mb": 31740.1875, "gpu": {"utilization": 0.0, "memory_used_mb": 14.0, "memory_total_mb": 23034.0}}
{"timestamp": "2026-05-06T00:03:57.870773+00:00", "hostname": "frank-XPS-8960", "gpu_type": "NVIDIA L4", "gpu_count": 1, "cpu_percent": 0.2, "memory_percent": 17.5, "memory_used_mb": 5554.30078125, "memory_total_mb": 31740.1875, "gpu": {"utilization": 0.0, "memory_used_mb": 14.0, "memory_total_mb": 23034.0}}
{"timestamp": "2026-05-06T00:03:59.215052+00:00", "hostname": "frank-XPS-8960", "gpu_type": "NVIDIA L4", "gpu_count": 1, "cpu_percent": 0.0, "memory_percent": 17.5, "memory_used_mb": 5563.69140625, "memory_total_mb": 31740.1875, "gpu": {"utilization": 0.0, "memory_used_mb": 14.0, "memory_total_mb": 23034.0}}
{"timestamp": "2026-05-06T00:04:08.388114+00:00", "hostname": "frank-XPS-8960", "gpu_type": "NVIDIA L4", "gpu_count": 1, "cpu_percent": 0.0, "memory_percent": 17.5, "memory_used_mb": 5554.75, "memory_total_mb": 31740.1875, "gpu": {"utilization": 0.0, "memory_used_mb": 14.0, "memory_total_mb": 23034.0}}
{"timestamp": "2026-05-06T00:04:09.732327+00:00", "hostname": "frank-XPS-8960", "gpu_type": "NVIDIA L4", "gpu_count": 1, "cpu_percent": 0.3, "memory_percent": 17.5, "memory_used_mb": 5565.75390625, "memory_total_mb": 31740.1875, "gpu": {"utilization": 0.0, "memory_used_mb": 14.0, "memory_total_mb": 23034.0}}
{"timestamp": "2026-05-06T00:04:18.905692+00:00", "hostname": "frank-XPS-8960", "gpu_type": "NVIDIA L4", "gpu_count": 1, "cpu_percent": 0.2, "memory_percent": 17.5, "memory_used_mb": 5549.35546875, "memory_total_mb": 31740.1875, "gpu": {"utilization": 0.0, "memory_used_mb": 14.0, "memory_total_mb": 23034.0}}
{"timestamp": "2026-05-06T00:04:20.249539+00:00", "hostname": "frank-XPS-8960", "gpu_type": "NVIDIA L4", "gpu_count": 1, "cpu_percent": 0.0, "memory_percent": 17.5, "memory_used_mb": 5549.5078125, "memory_total_mb": 31740.1875, "gpu": {"utilization": 0.0, "memory_used_mb": 14.0, "memory_total_mb": 23034.0}}
{"timestamp": "2026-05-06T00:04:29.426236+00:00", "hostname": "frank-XPS-8960", "gpu_type": "NVIDIA L4", "gpu_count": 1, "cpu_percent": 0.1, "memory_percent": 17.5, "memory_used_mb": 5548.26953125, "memory_total_mb": 31740.1875, "gpu": {"utilization": 0.0, "memory_used_mb": 14.0, "memory_total_mb": 23034.0}}
{"timestamp": "2026-05-06T00:04:30.770173+00:00", "hostname": "frank-XPS-8960", "gpu_type": "NVIDIA L4", "gpu_count": 1, "cpu_percent": 0.4, "memory_percent": 17.5, "memory_used_mb": 5553.0078125, "memory_total_mb": 31740.1875, "gpu": {"utilization": 0.0, "memory_used_mb": 14.0, "memory_total_mb": 23034.0}}
{"timestamp": "2026-05-06T00:04:39.946014+00:00", "hostname": "frank-XPS-8960", "gpu_type": "NVIDIA L4", "gpu_count": 1, "cpu_percent": 0.1, "memory_percent": 17.5, "memory_used_mb": 5549.640625, "memory_total_mb": 31740.1875, "gpu": {"utilization": 0.0, "memory_used_mb": 14.0, "memory_total_mb": 23034.0}}
{"timestamp": "2026-05-06T00:04:41.288789+00:00", "hostname": "frank-XPS-8960", "gpu_type": "NVIDIA L4", "gpu_count": 1, "cpu_percent": 0.1, "memory_percent": 17.5, "memory_used_mb": 5562.1328125, "memory_total_mb": 31740.1875, "gpu": {"utilization": 0.0, "memory_used_mb": 14.0, "memory_total_mb": 23034.0}}
{"timestamp": "2026-05-06T00:04:50.463444+00:00", "hostname": "frank-XPS-8960", "gpu_type": "NVIDIA L4", "gpu_count": 1, "cpu_percent": 0.0, "memory_percent": 17.5, "memory_used_mb": 5555.8828125, "memory_total_mb": 31740.1875, "gpu": {"utilization": 0.0, "memory_used_mb": 14.0, "memory_total_mb": 23034.0}}
{"timestamp": "2026-05-06T00:04:51.805360+00:00", "hostname": "frank-XPS-8960", "gpu_type": "NVIDIA L4", "gpu_count": 1, "cpu_percent": 0.2, "memory_percent": 17.5, "memory_used_mb": 5551.91796875, "memory_total_mb": 31740.1875, "gpu": {"utilization": 0.0, "memory_used_mb": 14.0, "memory_total_mb": 23034.0}}
{"timestamp": "2026-05-06T00:05:00.980235+00:00", "hostname": "frank-XPS-8960", "gpu_type": "NVIDIA L4", "gpu_count": 1, "cpu_percent": 0.3, "memory_percent": 17.5, "memory_used_mb": 5557.359375, "memory_total_mb": 31740.1875, "gpu": {"utilization": 0.0, "memory_used_mb": 14.0, "memory_total_mb": 23034.0}}
{"timestamp": "2026-05-06T00:05:02.325942+00:00", "hostname": "frank-XPS-8960", "gpu_type": "NVIDIA L4", "gpu_count": 1, "cpu_percent": 0.3, "memory_percent": 17.5, "memory_used_mb": 5566.55859375, "memory_total_mb": 31740.1875, "gpu": {"utilization": 0.0, "memory_used_mb": 14.0, "memory_total_mb": 23034.0}}
{"timestamp": "2026-05-06T00:05:11.497131+00:00", "hostname": "frank-XPS-8960", "gpu_type": "NVIDIA L4", "gpu_count": 1, "cpu_percent": 0.2, "memory_percent": 17.5, "memory_used_mb": 5542.8515625, "memory_total_mb": 31740.1875, "gpu": {"utilization": 0.0, "memory_used_mb": 14.0, "memory_total_mb": 23034.0}}
{"timestamp": "2026-05-06T00:05:12.846311+00:00", "hostname": "frank-XPS-8960", "gpu_type": "NVIDIA L4", "gpu_count": 1, "cpu_percent": 0.4, "memory_percent": 17.5, "memory_used_mb": 5548.78515625, "memory_total_mb": 31740.1875, "gpu": {"utilization": 0.0, "memory_used_mb": 14.0, "memory_total_mb": 23034.0}}
{"timestamp": "2026-05-06T00:05:22.015115+00:00", "hostname": "frank-XPS-8960", "gpu_type": "NVIDIA L4", "gpu_count": 1, "cpu_percent": 0.1, "memory_percent": 17.5, "memory_used_mb": 5543.65625, "memory_total_mb": 31740.1875, "gpu": {"utilization": 0.0, "memory_used_mb": 14.0, "memory_total_mb": 23034.0}}
{"timestamp": "2026-05-06T00:05:23.364499+00:00", "hostname": "frank-XPS-8960", "gpu_type": "NVIDIA L4", "gpu_count": 1, "cpu_percent": 0.1, "memory_percent": 17.5, "memory_used_mb": 5554.71875, "memory_total_mb": 31740.1875, "gpu": {"utilization": 0.0, "memory_used_mb": 14.0, "memory_total_mb": 23034.0}}
{"timestamp": "2026-05-06T00:05:32.535703+00:00", "hostname": "frank-XPS-8960", "gpu_type": "NVIDIA L4", "gpu_count": 1, "cpu_percent": 0.1, "memory_percent": 17.5, "memory_used_mb": 5546.09765625, "memory_total_mb": 31740.1875, "gpu": {"utilization": 0.0, "memory_used_mb": 14.0, "memory_total_mb": 23034.0}}
{"timestamp": "2026-05-06T00:05:33.885259+00:00", "hostname": "frank-XPS-8960", "gpu_type": "NVIDIA L4", "gpu_count": 1, "cpu_percent": 0.1, "memory_percent": 17.5, "memory_used_mb": 5557.41015625, "memory_total_mb": 31740.1875, "gpu": {"utilization": 0.0, "memory_used_mb": 14.0, "memory_total_mb": 23034.0}}
{"timestamp": "2026-05-06T00:05:43.056765+00:00", "hostname": "frank-XPS-8960", "gpu_type": "NVIDIA L4", "gpu_count": 1, "cpu_percent": 0.2, "memory_percent": 17.5, "memory_used_mb": 5554.4375, "memory_total_mb": 31740.1875, "gpu": {"utilization": 0.0, "memory_used_mb": 14.0, "memory_total_mb": 23034.0}}
{"timestamp": "2026-05-06T00:05:44.403022+00:00", "hostname": "frank-XPS-8960", "gpu_type": "NVIDIA L4", "gpu_count": 1, "cpu_percent": 0.1, "memory_percent": 17.5, "memory_used_mb": 5560.875, "memory_total_mb": 31740.1875, "gpu": {"utilization": 0.0, "memory_used_mb": 14.0, "memory_total_mb": 23034.0}}
{"timestamp": "2026-05-06T00:05:53.574368+00:00", "hostname": "frank-XPS-8960", "gpu_type": "NVIDIA L4", "gpu_count": 1, "cpu_percent": 0.1, "memory_percent": 17.5, "memory_used_mb": 5553.58203125, "memory_total_mb": 31740.1875, "gpu": {"utilization": 0.0, "memory_used_mb": 14.0, "memory_total_mb": 23034.0}}
{"timestamp": "2026-05-06T00:05:54.921041+00:00", "hostname": "frank-XPS-8960", "gpu_type": "NVIDIA L4", "gpu_count": 1, "cpu_percent": 0.4, "memory_percent": 17.5, "memory_used_mb": 5558.08203125, "memory_total_mb": 31740.1875, "gpu": {"utilization": 0.0, "memory_used_mb": 14.0, "memory_total_mb": 23034.0}}
{"timestamp": "2026-05-06T00:06:04.093900+00:00", "hostname": "frank-XPS-8960", "gpu_type": "NVIDIA L4", "gpu_count": 1, "cpu_percent": 0.3, "memory_percent": 17.5, "memory_used_mb": 5551.90625, "memory_total_mb": 31740.1875, "gpu": {"utilization": 0.0, "memory_used_mb": 14.0, "memory_total_mb": 23034.0}}
{"timestamp": "2026-05-06T00:06:05.438872+00:00", "hostname": "frank-XPS-8960", "gpu_type": "NVIDIA L4", "gpu_count": 1, "cpu_percent": 0.1, "memory_percent": 17.5, "memory_used_mb": 5559.50390625, "memory_total_mb": 31740.1875, "gpu": {"utilization": 0.0, "memory_used_mb": 14.0, "memory_total_mb": 23034.0}}
{"timestamp": "2026-05-06T00:06:14.614257+00:00", "hostname": "frank-XPS-8960", "gpu_type": "NVIDIA L4", "gpu_count": 1, "cpu_percent": 0.1, "memory_percent": 17.5, "memory_used_mb": 5556.08984375, "memory_total_mb": 31740.1875, "gpu": {"utilization": 0.0, "memory_used_mb": 14.0, "memory_total_mb": 23034.0}}
{"timestamp": "2026-05-06T00:06:15.956271+00:00", "hostname": "frank-XPS-8960", "gpu_type": "NVIDIA L4", "gpu_count": 1, "cpu_percent": 0.3, "memory_percent": 17.5, "memory_used_mb": 5560.65625, "memory_total_mb": 31740.1875, "gpu": {"utilization": 0.0, "memory_used_mb": 14.0, "memory_total_mb": 23034.0}}
{"timestamp": "2026-05-06T00:06:25.132654+00:00", "hostname": "frank-XPS-8960", "gpu_type": "NVIDIA L4", "gpu_count": 1, "cpu_percent": 0.1, "memory_percent": 17.5, "memory_used_mb": 5545.20703125, "memory_total_mb": 31740.1875, "gpu": {"utilization": 0.0, "memory_used_mb": 14.0, "memory_total_mb": 23034.0}}
{"timestamp": "2026-05-06T00:06:26.473868+00:00", "hostname": "frank-XPS-8960", "gpu_type": "NVIDIA L4", "gpu_count": 1, "cpu_percent": 0.0, "memory_percent": 17.5, "memory_used_mb": 5549.51171875, "memory_total_mb": 31740.1875, "gpu": {"utilization": 0.0, "memory_used_mb": 14.0, "memory_total_mb": 23034.0}}
{"timestamp": "2026-05-06T00:06:35.649359+00:00", "hostname": "frank-XPS-8960", "gpu_type": "NVIDIA L4", "gpu_count": 1, "cpu_percent": 0.1, "memory_percent": 17.5, "memory_used_mb": 5545.671875, "memory_total_mb": 31740.1875, "gpu": {"utilization": 0.0, "memory_used_mb": 14.0, "memory_total_mb": 23034.0}}
{"timestamp": "2026-05-06T00:06:36.990822+00:00", "hostname": "frank-XPS-8960", "gpu_type": "NVIDIA L4", "gpu_count": 1, "cpu_percent": 0.2, "memory_percent": 17.5, "memory_used_mb": 5552.953125, "memory_total_mb": 31740.1875, "gpu": {"utilization": 0.0, "memory_used_mb": 14.0, "memory_total_mb": 23034.0}}
{"timestamp": "2026-05-06T00:06:46.167015+00:00", "hostname": "frank-XPS-8960", "gpu_type": "NVIDIA L4", "gpu_count": 1, "cpu_percent": 0.3, "memory_percent": 17.5, "memory_used_mb": 5546.36328125, "memory_total_mb": 31740.1875, "gpu": {"utilization": 0.0, "memory_used_mb": 14.0, "memory_total_mb": 23034.0}}
{"timestamp": "2026-05-06T00:06:47.508581+00:00", "hostname": "frank-XPS-8960", "gpu_type": "NVIDIA L4", "gpu_count": 1, "cpu_percent": 0.1, "memory_percent": 17.5, "memory_used_mb": 5541.296875, "memory_total_mb": 31740.1875, "gpu": {"utilization": 0.0, "memory_used_mb": 14.0, "memory_total_mb": 23034.0}}
{"timestamp": "2026-05-06T00:06:56.683825+00:00", "hostname": "frank-XPS-8960", "gpu_type": "NVIDIA L4", "gpu_count": 1, "cpu_percent": 0.2, "memory_percent": 17.5, "memory_used_mb": 5541.37109375, "memory_total_mb": 31740.1875, "gpu": {"utilization": 0.0, "memory_used_mb": 14.0, "memory_total_mb": 23034.0}}
{"timestamp": "2026-05-06T00:06:58.025745+00:00", "hostname": "frank-XPS-8960", "gpu_type": "NVIDIA L4", "gpu_count": 1, "cpu_percent": 0.3, "memory_percent": 17.5, "memory_used_mb": 5540.34375, "memory_total_mb": 31740.1875, "gpu": {"utilization": 0.0, "memory_used_mb": 14.0, "memory_total_mb": 23034.0}}
{"timestamp": "2026-05-06T00:07:07.201346+00:00", "hostname": "frank-XPS-8960", "gpu_type": "NVIDIA L4", "gpu_count": 1, "cpu_percent": 0.1, "memory_percent": 17.5, "memory_used_mb": 5553.359375, "memory_total_mb": 31740.1875, "gpu": {"utilization": 0.0, "memory_used_mb": 14.0, "memory_total_mb": 23034.0}}
{"timestamp": "2026-05-06T00:07:08.545728+00:00", "hostname": "frank-XPS-8960", "gpu_type": "NVIDIA L4", "gpu_count": 1, "cpu_percent": 0.1, "memory_percent": 17.5, "memory_used_mb": 5560.66015625, "memory_total_mb": 31740.1875, "gpu": {"utilization": 0.0, "memory_used_mb": 14.0, "memory_total_mb": 23034.0}}
{"timestamp": "2026-05-06T00:07:17.718200+00:00", "hostname": "frank-XPS-8960", "gpu_type": "NVIDIA L4", "gpu_count": 1, "cpu_percent": 0.1, "memory_percent": 17.5, "memory_used_mb": 5549.0078125, "memory_total_mb": 31740.1875, "gpu": {"utilization": 0.0, "memory_used_mb": 14.0, "memory_total_mb": 23034.0}}
{"timestamp": "2026-05-06T00:07:19.063583+00:00", "hostname": "frank-XPS-8960", "gpu_type": "NVIDIA L4", "gpu_count": 1, "cpu_percent": 0.2, "memory_percent": 17.5, "memory_used_mb": 5543.88671875, "memory_total_mb": 31740.1875, "gpu": {"utilization": 0.0, "memory_used_mb": 14.0, "memory_total_mb": 23034.0}}
{"timestamp": "2026-05-06T00:07:28.235586+00:00", "hostname": "frank-XPS-8960", "gpu_type": "NVIDIA L4", "gpu_count": 1, "cpu_percent": 0.1, "memory_percent": 17.5, "memory_used_mb": 5545.08203125, "memory_total_mb": 31740.1875, "gpu": {"utilization": 0.0, "memory_used_mb": 14.0, "memory_total_mb": 23034.0}}
{"timestamp": "2026-05-06T00:07:29.580392+00:00", "hostname": "frank-XPS-8960", "gpu_type": "NVIDIA L4", "gpu_count": 1, "cpu_percent": 0.1, "memory_percent": 17.5, "memory_used_mb": 5552.14453125, "memory_total_mb": 31740.1875, "gpu": {"utilization": 0.0, "memory_used_mb": 14.0, "memory_total_mb": 23034.0}}
{"timestamp": "2026-05-06T00:07:38.752627+00:00", "hostname": "frank-XPS-8960", "gpu_type": "NVIDIA L4", "gpu_count": 1, "cpu_percent": 0.3, "memory_percent": 17.5, "memory_used_mb": 5551.61328125, "memory_total_mb": 31740.1875, "gpu": {"utilization": 0.0, "memory_used_mb": 14.0, "memory_total_mb": 23034.0}}
{"timestamp": "2026-05-06T00:07:40.098081+00:00", "hostname": "frank-XPS-8960", "gpu_type": "NVIDIA L4", "gpu_count": 1, "cpu_percent": 0.1, "memory_percent": 17.5, "memory_used_mb": 5551.515625, "memory_total_mb": 31740.1875, "gpu": {"utilization": 0.0, "memory_used_mb": 14.0, "memory_total_mb": 23034.0}}
{"timestamp": "2026-05-06T00:07:49.269458+00:00", "hostname": "frank-XPS-8960", "gpu_type": "NVIDIA L4", "gpu_count": 1, "cpu_percent": 0.1, "memory_percent": 17.5, "memory_used_mb": 5545.90234375, "memory_total_mb": 31740.1875, "gpu": {"utilization": 0.0, "memory_used_mb": 14.0, "memory_total_mb": 23034.0}}
{"timestamp": "2026-05-06T00:07:50.614878+00:00", "hostname": "frank-XPS-8960", "gpu_type": "NVIDIA L4", "gpu_count": 1, "cpu_percent": 0.1, "memory_percent": 17.5, "memory_used_mb": 5556.25390625, "memory_total_mb": 31740.1875, "gpu": {"utilization": 0.0, "memory_used_mb": 14.0, "memory_total_mb": 23034.0}}
{"timestamp": "2026-05-06T00:07:59.786681+00:00", "hostname": "frank-XPS-8960", "gpu_type": "NVIDIA L4", "gpu_count": 1, "cpu_percent": 0.2, "memory_percent": 17.5, "memory_used_mb": 5564.796875, "memory_total_mb": 31740.1875, "gpu": {"utilization": 0.0, "memory_used_mb": 14.0, "memory_total_mb": 23034.0}}
{"timestamp": "2026-05-06T00:08:01.132805+00:00", "hostname": "frank-XPS-8960", "gpu_type": "NVIDIA L4", "gpu_count": 1, "cpu_percent": 0.2, "memory_percent": 17.5, "memory_used_mb": 5568.01171875, "memory_total_mb": 31740.1875, "gpu": {"utilization": 0.0, "memory_used_mb": 14.0, "memory_total_mb": 23034.0}}
{"timestamp": "2026-05-06T00:08:10.305725+00:00", "hostname": "frank-XPS-8960", "gpu_type": "NVIDIA L4", "gpu_count": 1, "cpu_percent": 0.1, "memory_percent": 17.5, "memory_used_mb": 5550.875, "memory_total_mb": 31740.1875, "gpu": {"utilization": 0.0, "memory_used_mb": 14.0, "memory_total_mb": 23034.0}}
{"timestamp": "2026-05-06T00:08:11.650373+00:00", "hostname": "frank-XPS-8960", "gpu_type": "NVIDIA L4", "gpu_count": 1, "cpu_percent": 0.1, "memory_percent": 17.5, "memory_used_mb": 5560.48046875, "memory_total_mb": 31740.1875, "gpu": {"utilization": 0.0, "memory_used_mb": 14.0, "memory_total_mb": 23034.0}}
{"timestamp": "2026-05-06T00:08:20.825778+00:00", "hostname": "frank-XPS-8960", "gpu_type": "NVIDIA L4", "gpu_count": 1, "cpu_percent": 0.0, "memory_percent": 17.5, "memory_used_mb": 5568.73828125, "memory_total_mb": 31740.1875, "gpu": {"utilization": 0.0, "memory_used_mb": 14.0, "memory_total_mb": 23034.0}}
{"timestamp": "2026-05-06T00:08:22.169205+00:00", "hostname": "frank-XPS-8960", "gpu_type": "NVIDIA L4", "gpu_count": 1, "cpu_percent": 0.1, "memory_percent": 17.5, "memory_used_mb": 5557.1484375, "memory_total_mb": 31740.1875, "gpu": {"utilization": 0.0, "memory_used_mb": 14.0, "memory_total_mb": 23034.0}}
{"timestamp": "2026-05-06T00:08:31.342706+00:00", "hostname": "frank-XPS-8960", "gpu_type": "NVIDIA L4", "gpu_count": 1, "cpu_percent": 0.1, "memory_percent": 17.5, "memory_used_mb": 5546.1796875, "memory_total_mb": 31740.1875, "gpu": {"utilization": 0.0, "memory_used_mb": 14.0, "memory_total_mb": 23034.0}}
{"timestamp": "2026-05-06T00:08:32.686117+00:00", "hostname": "frank-XPS-8960", "gpu_type": "NVIDIA L4", "gpu_count": 1, "cpu_percent": 0.1, "memory_percent": 17.5, "memory_used_mb": 5548.30078125, "memory_total_mb": 31740.1875, "gpu": {"utilization": 0.0, "memory_used_mb": 14.0, "memory_total_mb": 23034.0}}
{"timestamp": "2026-05-06T00:08:41.859684+00:00", "hostname": "frank-XPS-8960", "gpu_type": "NVIDIA L4", "gpu_count": 1, "cpu_percent": 0.1, "memory_percent": 17.5, "memory_used_mb": 5547.5, "memory_total_mb": 31740.1875, "gpu": {"utilization": 0.0, "memory_used_mb": 14.0, "memory_total_mb": 23034.0}}
{"timestamp": "2026-05-06T00:08:43.203803+00:00", "hostname": "frank-XPS-8960", "gpu_type": "NVIDIA L4", "gpu_count": 1, "cpu_percent": 0.1, "memory_percent": 17.5, "memory_used_mb": 5556.84765625, "memory_total_mb": 31740.1875, "gpu": {"utilization": 0.0, "memory_used_mb": 14.0, "memory_total_mb": 23034.0}}
{"timestamp": "2026-05-06T00:08:52.376531+00:00", "hostname": "frank-XPS-8960", "gpu_type": "NVIDIA L4", "gpu_count": 1, "cpu_percent": 0.1, "memory_percent": 17.5, "memory_used_mb": 5554.6171875, "memory_total_mb": 31740.1875, "gpu": {"utilization": 0.0, "memory_used_mb": 14.0, "memory_total_mb": 23034.0}}
{"timestamp": "2026-05-06T00:08:53.723894+00:00", "hostname": "frank-XPS-8960", "gpu_type": "NVIDIA L4", "gpu_count": 1, "cpu_percent": 0.4, "memory_percent": 17.5, "memory_used_mb": 5556.75, "memory_total_mb": 31740.1875, "gpu": {"utilization": 0.0, "memory_used_mb": 14.0, "memory_total_mb": 23034.0}}
{"timestamp": "2026-05-06T00:09:02.893283+00:00", "hostname": "frank-XPS-8960", "gpu_type": "NVIDIA L4", "gpu_count": 1, "cpu_percent": 0.1, "memory_percent": 17.5, "memory_used_mb": 5546.6328125, "memory_total_mb": 31740.1875, "gpu": {"utilization": 0.0, "memory_used_mb": 14.0, "memory_total_mb": 23034.0}}
{"timestamp": "2026-05-06T00:09:04.242448+00:00", "hostname": "frank-XPS-8960", "gpu_type": "NVIDIA L4", "gpu_count": 1, "cpu_percent": 0.1, "memory_percent": 17.5, "memory_used_mb": 5557.5546875, "memory_total_mb": 31740.1875, "gpu": {"utilization": 0.0, "memory_used_mb": 14.0, "memory_total_mb": 23034.0}}
{"timestamp": "2026-05-06T00:09:13.410610+00:00", "hostname": "frank-XPS-8960", "gpu_type": "NVIDIA L4", "gpu_count": 1, "cpu_percent": 0.1, "memory_percent": 17.5, "memory_used_mb": 5547.546875, "memory_total_mb": 31740.1875, "gpu": {"utilization": 0.0, "memory_used_mb": 14.0, "memory_total_mb": 23034.0}}
{"timestamp": "2026-05-06T00:09:14.759289+00:00", "hostname": "frank-XPS-8960", "gpu_type": "NVIDIA L4", "gpu_count": 1, "cpu_percent": 0.1, "memory_percent": 17.5, "memory_used_mb": 5558.08984375, "memory_total_mb": 31740.1875, "gpu": {"utilization": 0.0, "memory_used_mb": 14.0, "memory_total_mb": 23034.0}}
{"timestamp": "2026-05-06T00:09:23.927340+00:00", "hostname": "frank-XPS-8960", "gpu_type": "NVIDIA L4", "gpu_count": 1, "cpu_percent": 0.3, "memory_percent": 17.5, "memory_used_mb": 5552.61328125, "memory_total_mb": 31740.1875, "gpu": {"utilization": 0.0, "memory_used_mb": 14.0, "memory_total_mb": 23034.0}}
{"timestamp": "2026-05-06T00:09:25.276238+00:00", "hostname": "frank-XPS-8960", "gpu_type": "NVIDIA L4", "gpu_count": 1, "cpu_percent": 0.6, "memory_percent": 17.5, "memory_used_mb": 5552.8671875, "memory_total_mb": 31740.1875, "gpu": {"utilization": 0.0, "memory_used_mb": 14.0, "memory_total_mb": 23034.0}}
{"timestamp": "2026-05-06T00:09:34.444106+00:00", "hostname": "frank-XPS-8960", "gpu_type": "NVIDIA L4", "gpu_count": 1, "cpu_percent": 0.1, "memory_percent": 17.5, "memory_used_mb": 5543.34375, "memory_total_mb": 31740.1875, "gpu": {"utilization": 0.0, "memory_used_mb": 14.0, "memory_total_mb": 23034.0}}
{"timestamp": "2026-05-06T00:09:35.793622+00:00", "hostname": "frank-XPS-8960", "gpu_type": "NVIDIA L4", "gpu_count": 1, "cpu_percent": 0.3, "memory_percent": 17.5, "memory_used_mb": 5555.50390625, "memory_total_mb": 31740.1875, "gpu": {"utilization": 0.0, "memory_used_mb": 14.0, "memory_total_mb": 23034.0}}
{"timestamp": "2026-05-06T00:09:44.961436+00:00", "hostname": "frank-XPS-8960", "gpu_type": "NVIDIA L4", "gpu_count": 1, "cpu_percent": 0.2, "memory_percent": 17.6, "memory_used_mb": 5591.16015625, "memory_total_mb": 31740.1875, "gpu": {"utilization": 0.0, "memory_used_mb": 14.0, "memory_total_mb": 23034.0}}
{"timestamp": "2026-05-06T00:09:46.310876+00:00", "hostname": "frank-XPS-8960", "gpu_type": "NVIDIA L4", "gpu_count": 1, "cpu_percent": 0.1, "memory_percent": 17.6, "memory_used_mb": 5591.00390625, "memory_total_mb": 31740.1875, "gpu": {"utilization": 0.0, "memory_used_mb": 14.0, "memory_total_mb": 23034.0}}
{"timestamp": "2026-05-06T00:09:55.477914+00:00", "hostname": "frank-XPS-8960", "gpu_type": "NVIDIA L4", "gpu_count": 1, "cpu_percent": 0.4, "memory_percent": 17.6, "memory_used_mb": 5587.68359375, "memory_total_mb": 31740.1875, "gpu": {"utilization": 0.0, "memory_used_mb": 14.0, "memory_total_mb": 23034.0}}
{"timestamp": "2026-05-06T00:09:56.829485+00:00", "hostname": "frank-XPS-8960", "gpu_type": "NVIDIA L4", "gpu_count": 1, "cpu_percent": 0.2, "memory_percent": 17.6, "memory_used_mb": 5589.8046875, "memory_total_mb": 31740.1875, "gpu": {"utilization": 0.0, "memory_used_mb": 14.0, "memory_total_mb": 23034.0}}
{"timestamp": "2026-05-06T00:10:05.995742+00:00", "hostname": "frank-XPS-8960", "gpu_type": "NVIDIA L4", "gpu_count": 1, "cpu_percent": 0.1, "memory_percent": 17.5, "memory_used_mb": 5557.53125, "memory_total_mb": 31740.1875, "gpu": {"utilization": 0.0, "memory_used_mb": 14.0, "memory_total_mb": 23034.0}}
{"timestamp": "2026-05-06T00:10:07.346743+00:00", "hostname": "frank-XPS-8960", "gpu_type": "NVIDIA L4", "gpu_count": 1, "cpu_percent": 0.1, "memory_percent": 17.5, "memory_used_mb": 5566.58984375, "memory_total_mb": 31740.1875, "gpu": {"utilization": 0.0, "memory_used_mb": 14.0, "memory_total_mb": 23034.0}}
{"timestamp": "2026-05-06T00:10:16.514453+00:00", "hostname": "frank-XPS-8960", "gpu_type": "NVIDIA L4", "gpu_count": 1, "cpu_percent": 0.5, "memory_percent": 17.5, "memory_used_mb": 5542.7734375, "memory_total_mb": 31740.1875, "gpu": {"utilization": 0.0, "memory_used_mb": 14.0, "memory_total_mb": 23034.0}}
{"timestamp": "2026-05-06T00:10:17.863478+00:00", "hostname": "frank-XPS-8960", "gpu_type": "NVIDIA L4", "gpu_count": 1, "cpu_percent": 0.1, "memory_percent": 17.5, "memory_used_mb": 5541.6640625, "memory_total_mb": 31740.1875, "gpu": {"utilization": 0.0, "memory_used_mb": 14.0, "memory_total_mb": 23034.0}}
{"timestamp": "2026-05-06T00:10:27.031334+00:00", "hostname": "frank-XPS-8960", "gpu_type": "NVIDIA L4", "gpu_count": 1, "cpu_percent": 0.2, "memory_percent": 17.5, "memory_used_mb": 5567.1015625, "memory_total_mb": 31740.1875, "gpu": {"utilization": 0.0, "memory_used_mb": 14.0, "memory_total_mb": 23034.0}}
{"timestamp": "2026-05-06T00:10:28.380766+00:00", "hostname": "frank-XPS-8960", "gpu_type": "NVIDIA L4", "gpu_count": 1, "cpu_percent": 0.5, "memory_percent": 17.6, "memory_used_mb": 5577.96484375, "memory_total_mb": 31740.1875, "gpu": {"utilization": 0.0, "memory_used_mb": 14.0, "memory_total_mb": 23034.0}}
{"timestamp": "2026-05-06T00:10:37.547655+00:00", "hostname": "frank-XPS-8960", "gpu_type": "NVIDIA L4", "gpu_count": 1, "cpu_percent": 0.2, "memory_percent": 17.5, "memory_used_mb": 5557.4609375, "memory_total_mb": 31740.1875, "gpu": {"utilization": 0.0, "memory_used_mb": 14.0, "memory_total_mb": 23034.0}}
{"timestamp": "2026-05-06T00:10:38.898769+00:00", "hostname": "frank-XPS-8960", "gpu_type": "NVIDIA L4", "gpu_count": 1, "cpu_percent": 0.2, "memory_percent": 17.5, "memory_used_mb": 5550.125, "memory_total_mb": 31740.1875, "gpu": {"utilization": 0.0, "memory_used_mb": 14.0, "memory_total_mb": 23034.0}}
{"timestamp": "2026-05-06T00:10:48.065306+00:00", "hostname": "frank-XPS-8960", "gpu_type": "NVIDIA L4", "gpu_count": 1, "cpu_percent": 0.9, "memory_percent": 17.6, "memory_used_mb": 5576.7734375, "memory_total_mb": 31740.1875, "gpu": {"utilization": 0.0, "memory_used_mb": 14.0, "memory_total_mb": 23034.0}}
{"timestamp": "2026-05-06T00:10:49.415592+00:00", "hostname": "frank-XPS-8960", "gpu_type": "NVIDIA L4", "gpu_count": 1, "cpu_percent": 1.1, "memory_percent": 17.6, "memory_used_mb": 5576.97265625, "memory_total_mb": 31740.1875, "gpu": {"utilization": 0.0, "memory_used_mb": 14.0, "memory_total_mb": 23034.0}}
{"timestamp": "2026-05-06T00:10:58.581795+00:00", "hostname": "frank-XPS-8960", "gpu_type": "NVIDIA L4", "gpu_count": 1, "cpu_percent": 0.1, "memory_percent": 17.5, "memory_used_mb": 5565.1796875, "memory_total_mb": 31740.1875, "gpu": {"utilization": 0.0, "memory_used_mb": 14.0, "memory_total_mb": 23034.0}}
{"timestamp": "2026-05-06T00:10:59.932233+00:00", "hostname": "frank-XPS-8960", "gpu_type": "NVIDIA L4", "gpu_count": 1, "cpu_percent": 0.9, "memory_percent": 17.5, "memory_used_mb": 5567.08984375, "memory_total_mb": 31740.1875, "gpu": {"utilization": 0.0, "memory_used_mb": 14.0, "memory_total_mb": 23034.0}}
{"timestamp": "2026-05-06T00:11:09.099181+00:00", "hostname": "frank-XPS-8960", "gpu_type": "NVIDIA L4", "gpu_count": 1, "cpu_percent": 0.1, "memory_percent": 17.5, "memory_used_mb": 5568.859375, "memory_total_mb": 31740.1875, "gpu": {"utilization": 0.0, "memory_used_mb": 14.0, "memory_total_mb": 23034.0}}
{"timestamp": "2026-05-06T00:11:10.450813+00:00", "hostname": "frank-XPS-8960", "gpu_type": "NVIDIA L4", "gpu_count": 1, "cpu_percent": 0.1, "memory_percent": 17.5, "memory_used_mb": 5563.6171875, "memory_total_mb": 31740.1875, "gpu": {"utilization": 0.0, "memory_used_mb": 14.0, "memory_total_mb": 23034.0}}
{"timestamp": "2026-05-06T00:11:19.616338+00:00", "hostname": "frank-XPS-8960", "gpu_type": "NVIDIA L4", "gpu_count": 1, "cpu_percent": 0.1, "memory_percent": 17.5, "memory_used_mb": 5556.4140625, "memory_total_mb": 31740.1875, "gpu": {"utilization": 0.0, "memory_used_mb": 14.0, "memory_total_mb": 23034.0}}
{"timestamp": "2026-05-06T00:11:20.968439+00:00", "hostname": "frank-XPS-8960", "gpu_type": "NVIDIA L4", "gpu_count": 1, "cpu_percent": 0.1, "memory_percent": 17.5, "memory_used_mb": 5560.046875, "memory_total_mb": 31740.1875, "gpu": {"utilization": 0.0, "memory_used_mb": 14.0, "memory_total_mb": 23034.0}}
{"timestamp": "2026-05-06T00:11:30.133362+00:00", "hostname": "frank-XPS-8960", "gpu_type": "NVIDIA L4", "gpu_count": 1, "cpu_percent": 0.4, "memory_percent": 17.5, "memory_used_mb": 5566.125, "memory_total_mb": 31740.1875, "gpu": {"utilization": 0.0, "memory_used_mb": 14.0, "memory_total_mb": 23034.0}}
{"timestamp": "2026-05-06T00:11:31.485632+00:00", "hostname": "frank-XPS-8960", "gpu_type": "NVIDIA L4", "gpu_count": 1, "cpu_percent": 0.1, "memory_percent": 17.5, "memory_used_mb": 5570.32421875, "memory_total_mb": 31740.1875, "gpu": {"utilization": 0.0, "memory_used_mb": 14.0, "memory_total_mb": 23034.0}}
{"timestamp": "2026-05-06T00:11:40.650387+00:00", "hostname": "frank-XPS-8960", "gpu_type": "NVIDIA L4", "gpu_count": 1, "cpu_percent": 0.2, "memory_percent": 17.5, "memory_used_mb": 5546.140625, "memory_total_mb": 31740.1875, "gpu": {"utilization": 0.0, "memory_used_mb": 14.0, "memory_total_mb": 23034.0}}
{"timestamp": "2026-05-06T00:11:42.003653+00:00", "hostname": "frank-XPS-8960", "gpu_type": "NVIDIA L4", "gpu_count": 1, "cpu_percent": 0.3, "memory_percent": 17.5, "memory_used_mb": 5551.45703125, "memory_total_mb": 31740.1875, "gpu": {"utilization": 0.0, "memory_used_mb": 14.0, "memory_total_mb": 23034.0}}
{"timestamp": "2026-05-06T00:11:51.167784+00:00", "hostname": "frank-XPS-8960", "gpu_type": "NVIDIA L4", "gpu_count": 1, "cpu_percent": 0.0, "memory_percent": 17.5, "memory_used_mb": 5554.65234375, "memory_total_mb": 31740.1875, "gpu": {"utilization": 0.0, "memory_used_mb": 14.0, "memory_total_mb": 23034.0}}
{"timestamp": "2026-05-06T00:11:52.520594+00:00", "hostname": "frank-XPS-8960", "gpu_type": "NVIDIA L4", "gpu_count": 1, "cpu_percent": 0.1, "memory_percent": 17.5, "memory_used_mb": 5553.23046875, "memory_total_mb": 31740.1875, "gpu": {"utilization": 0.0, "memory_used_mb": 14.0, "memory_total_mb": 23034.0}}
{"timestamp": "2026-05-06T00:12:01.684820+00:00", "hostname": "frank-XPS-8960", "gpu_type": "NVIDIA L4", "gpu_count": 1, "cpu_percent": 0.4, "memory_percent": 17.5, "memory_used_mb": 5546.11328125, "memory_total_mb": 31740.1875, "gpu": {"utilization": 0.0, "memory_used_mb": 14.0, "memory_total_mb": 23034.0}}
{"timestamp": "2026-05-06T00:12:03.037424+00:00", "hostname": "frank-XPS-8960", "gpu_type": "NVIDIA L4", "gpu_count": 1, "cpu_percent": 0.2, "memory_percent": 17.5, "memory_used_mb": 5554.6875, "memory_total_mb": 31740.1875, "gpu": {"utilization": 0.0, "memory_used_mb": 14.0, "memory_total_mb": 23034.0}}
{"timestamp": "2026-05-06T00:12:12.202523+00:00", "hostname": "frank-XPS-8960", "gpu_type": "NVIDIA L4", "gpu_count": 1, "cpu_percent": 0.2, "memory_percent": 17.5, "memory_used_mb": 5561.78125, "memory_total_mb": 31740.1875, "gpu": {"utilization": 0.0, "memory_used_mb": 14.0, "memory_total_mb": 23034.0}}
{"timestamp": "2026-05-06T00:12:13.558045+00:00", "hostname": "frank-XPS-8960", "gpu_type": "NVIDIA L4", "gpu_count": 1, "cpu_percent": 0.1, "memory_percent": 17.5, "memory_used_mb": 5562.85546875, "memory_total_mb": 31740.1875, "gpu": {"utilization": 0.0, "memory_used_mb": 14.0, "memory_total_mb": 23034.0}}
{"timestamp": "2026-05-06T00:12:22.719592+00:00", "hostname": "frank-XPS-8960", "gpu_type": "NVIDIA L4", "gpu_count": 1, "cpu_percent": 0.1, "memory_percent": 17.5, "memory_used_mb": 5562.78515625, "memory_total_mb": 31740.1875, "gpu": {"utilization": 0.0, "memory_used_mb": 14.0, "memory_total_mb": 23034.0}}
{"timestamp": "2026-05-06T00:12:24.075201+00:00", "hostname": "frank-XPS-8960", "gpu_type": "NVIDIA L4", "gpu_count": 1, "cpu_percent": 0.2, "memory_percent": 17.6, "memory_used_mb": 5572.40234375, "memory_total_mb": 31740.1875, "gpu": {"utilization": 0.0, "memory_used_mb": 14.0, "memory_total_mb": 23034.0}}
{"timestamp": "2026-05-06T00:12:33.236229+00:00", "hostname": "frank-XPS-8960", "gpu_type": "NVIDIA L4", "gpu_count": 1, "cpu_percent": 0.4, "memory_percent": 17.5, "memory_used_mb": 5560.54296875, "memory_total_mb": 31740.1875, "gpu": {"utilization": 0.0, "memory_used_mb": 14.0, "memory_total_mb": 23034.0}}
{"timestamp": "2026-05-06T00:12:34.592852+00:00", "hostname": "frank-XPS-8960", "gpu_type": "NVIDIA L4", "gpu_count": 1, "cpu_percent": 0.4, "memory_percent": 17.6, "memory_used_mb": 5576.08984375, "memory_total_mb": 31740.1875, "gpu": {"utilization": 0.0, "memory_used_mb": 14.0, "memory_total_mb": 23034.0}}
{"timestamp": "2026-05-06T00:12:43.754735+00:00", "hostname": "frank-XPS-8960", "gpu_type": "NVIDIA L4", "gpu_count": 1, "cpu_percent": 0.1, "memory_percent": 17.5, "memory_used_mb": 5561.19921875, "memory_total_mb": 31740.1875, "gpu": {"utilization": 0.0, "memory_used_mb": 14.0, "memory_total_mb": 23034.0}}
{"timestamp": "2026-05-06T00:12:45.110039+00:00", "hostname": "frank-XPS-8960", "gpu_type": "NVIDIA L4", "gpu_count": 1, "cpu_percent": 0.4, "memory_percent": 17.5, "memory_used_mb": 5567.6484375, "memory_total_mb": 31740.1875, "gpu": {"utilization": 0.0, "memory_used_mb": 14.0, "memory_total_mb": 23034.0}}
{"timestamp": "2026-05-06T00:12:54.274838+00:00", "hostname": "frank-XPS-8960", "gpu_type": "NVIDIA L4", "gpu_count": 1, "cpu_percent": 0.4, "memory_percent": 17.6, "memory_used_mb": 5574.11328125, "memory_total_mb": 31740.1875, "gpu": {"utilization": 0.0, "memory_used_mb": 14.0, "memory_total_mb": 23034.0}}
{"timestamp": "2026-05-06T00:12:55.631385+00:00", "hostname": "frank-XPS-8960", "gpu_type": "NVIDIA L4", "gpu_count": 1, "cpu_percent": 0.1, "memory_percent": 17.6, "memory_used_mb": 5579.9296875, "memory_total_mb": 31740.1875, "gpu": {"utilization": 0.0, "memory_used_mb": 14.0, "memory_total_mb": 23034.0}}
{"timestamp": "2026-05-06T00:13:04.792332+00:00", "hostname": "frank-XPS-8960", "gpu_type": "NVIDIA L4", "gpu_count": 1, "cpu_percent": 0.2, "memory_percent": 17.5, "memory_used_mb": 5559.4296875, "memory_total_mb": 31740.1875, "gpu": {"utilization": 0.0, "memory_used_mb": 14.0, "memory_total_mb": 23034.0}}
{"timestamp": "2026-05-06T00:13:06.148565+00:00", "hostname": "frank-XPS-8960", "gpu_type": "NVIDIA L4", "gpu_count": 1, "cpu_percent": 0.1, "memory_percent": 17.5, "memory_used_mb": 5557.625, "memory_total_mb": 31740.1875, "gpu": {"utilization": 0.0, "memory_used_mb": 14.0, "memory_total_mb": 23034.0}}
{"timestamp": "2026-05-06T00:13:15.310068+00:00", "hostname": "frank-XPS-8960", "gpu_type": "NVIDIA L4", "gpu_count": 1, "cpu_percent": 0.2, "memory_percent": 17.6, "memory_used_mb": 5587.390625, "memory_total_mb": 31740.1875, "gpu": {"utilization": 0.0, "memory_used_mb": 14.0, "memory_total_mb": 23034.0}}
{"timestamp": "2026-05-06T00:13:16.664585+00:00", "hostname": "frank-XPS-8960", "gpu_type": "NVIDIA L4", "gpu_count": 1, "cpu_percent": 0.4, "memory_percent": 17.6, "memory_used_mb": 5578.07421875, "memory_total_mb": 31740.1875, "gpu": {"utilization": 0.0, "memory_used_mb": 14.0, "memory_total_mb": 23034.0}}
{"timestamp": "2026-05-06T00:13:25.826650+00:00", "hostname": "frank-XPS-8960", "gpu_type": "NVIDIA L4", "gpu_count": 1, "cpu_percent": 0.1, "memory_percent": 17.5, "memory_used_mb": 5561.796875, "memory_total_mb": 31740.1875, "gpu": {"utilization": 0.0, "memory_used_mb": 14.0, "memory_total_mb": 23034.0}}
{"timestamp": "2026-05-06T00:13:27.181735+00:00", "hostname": "frank-XPS-8960", "gpu_type": "NVIDIA L4", "gpu_count": 1, "cpu_percent": 1.5, "memory_percent": 17.6, "memory_used_mb": 5574.96875, "memory_total_mb": 31740.1875, "gpu": {"utilization": 0.0, "memory_used_mb": 14.0, "memory_total_mb": 23034.0}}
{"timestamp": "2026-05-06T00:13:36.344723+00:00", "hostname": "frank-XPS-8960", "gpu_type": "NVIDIA L4", "gpu_count": 1, "cpu_percent": 0.1, "memory_percent": 17.5, "memory_used_mb": 5561.58984375, "memory_total_mb": 31740.1875, "gpu": {"utilization": 0.0, "memory_used_mb": 14.0, "memory_total_mb": 23034.0}}
{"timestamp": "2026-05-06T00:13:37.702158+00:00", "hostname": "frank-XPS-8960", "gpu_type": "NVIDIA L4", "gpu_count": 1, "cpu_percent": 0.6, "memory_percent": 17.5, "memory_used_mb": 5567.890625, "memory_total_mb": 31740.1875, "gpu": {"utilization": 0.0, "memory_used_mb": 14.0, "memory_total_mb": 23034.0}}
{"timestamp": "2026-05-06T00:13:46.861977+00:00", "hostname": "frank-XPS-8960", "gpu_type": "NVIDIA L4", "gpu_count": 1, "cpu_percent": 0.2, "memory_percent": 17.5, "memory_used_mb": 5560.5390625, "memory_total_mb": 31740.1875, "gpu": {"utilization": 0.0, "memory_used_mb": 14.0, "memory_total_mb": 23034.0}}
{"timestamp": "2026-05-06T00:13:48.222443+00:00", "hostname": "frank-XPS-8960", "gpu_type": "NVIDIA L4", "gpu_count": 1, "cpu_percent": 0.1, "memory_percent": 17.5, "memory_used_mb": 5558.06640625, "memory_total_mb": 31740.1875, "gpu": {"utilization": 0.0, "memory_used_mb": 14.0, "memory_total_mb": 23034.0}}
{"timestamp": "2026-05-06T00:13:57.382257+00:00", "hostname": "frank-XPS-8960", "gpu_type": "NVIDIA L4", "gpu_count": 1, "cpu_percent": 0.1, "memory_percent": 17.5, "memory_used_mb": 5550.9921875, "memory_total_mb": 31740.1875, "gpu": {"utilization": 0.0, "memory_used_mb": 14.0, "memory_total_mb": 23034.0}}
{"timestamp": "2026-05-06T00:13:58.739690+00:00", "hostname": "frank-XPS-8960", "gpu_type": "NVIDIA L4", "gpu_count": 1, "cpu_percent": 0.1, "memory_percent": 17.5, "memory_used_mb": 5562.3046875, "memory_total_mb": 31740.1875, "gpu": {"utilization": 0.0, "memory_used_mb": 14.0, "memory_total_mb": 23034.0}}
{"timestamp": "2026-05-06T00:14:07.902348+00:00", "hostname": "frank-XPS-8960", "gpu_type": "NVIDIA L4", "gpu_count": 1, "cpu_percent": 0.0, "memory_percent": 17.5, "memory_used_mb": 5554.62109375, "memory_total_mb": 31740.1875, "gpu": {"utilization": 0.0, "memory_used_mb": 14.0, "memory_total_mb": 23034.0}}
{"timestamp": "2026-05-06T00:14:09.260243+00:00", "hostname": "frank-XPS-8960", "gpu_type": "NVIDIA L4", "gpu_count": 1, "cpu_percent": 0.1, "memory_percent": 17.5, "memory_used_mb": 5566.40234375, "memory_total_mb": 31740.1875, "gpu": {"utilization": 0.0, "memory_used_mb": 14.0, "memory_total_mb": 23034.0}}
{"timestamp": "2026-05-06T00:14:18.419889+00:00", "hostname": "frank-XPS-8960", "gpu_type": "NVIDIA L4", "gpu_count": 1, "cpu_percent": 0.1, "memory_percent": 17.5, "memory_used_mb": 5566.4296875, "memory_total_mb": 31740.1875, "gpu": {"utilization": 0.0, "memory_used_mb": 14.0, "memory_total_mb": 23034.0}}
{"timestamp": "2026-05-06T00:14:19.780759+00:00", "hostname": "frank-XPS-8960", "gpu_type": "NVIDIA L4", "gpu_count": 1, "cpu_percent": 0.0, "memory_percent": 17.6, "memory_used_mb": 5574.234375, "memory_total_mb": 31740.1875, "gpu": {"utilization": 0.0, "memory_used_mb": 14.0, "memory_total_mb": 23034.0}}
{"timestamp": "2026-05-06T00:14:28.936467+00:00", "hostname": "frank-XPS-8960", "gpu_type": "NVIDIA L4", "gpu_count": 1, "cpu_percent": 0.1, "memory_percent": 17.5, "memory_used_mb": 5561.25390625, "memory_total_mb": 31740.1875, "gpu": {"utilization": 0.0, "memory_used_mb": 14.0, "memory_total_mb": 23034.0}}
{"timestamp": "2026-05-06T00:14:30.298236+00:00", "hostname": "frank-XPS-8960", "gpu_type": "NVIDIA L4", "gpu_count": 1, "cpu_percent": 0.1, "memory_percent": 17.5, "memory_used_mb": 5565.3984375, "memory_total_mb": 31740.1875, "gpu": {"utilization": 0.0, "memory_used_mb": 14.0, "memory_total_mb": 23034.0}}
{"timestamp": "2026-05-06T00:14:39.453399+00:00", "hostname": "frank-XPS-8960", "gpu_type": "NVIDIA L4", "gpu_count": 1, "cpu_percent": 0.1, "memory_percent": 17.5, "memory_used_mb": 5566.1015625, "memory_total_mb": 31740.1875, "gpu": {"utilization": 0.0, "memory_used_mb": 14.0, "memory_total_mb": 23034.0}}
{"timestamp": "2026-05-06T00:14:40.815838+00:00", "hostname": "frank-XPS-8960", "gpu_type": "NVIDIA L4", "gpu_count": 1, "cpu_percent": 0.0, "memory_percent": 17.5, "memory_used_mb": 5562.71875, "memory_total_mb": 31740.1875, "gpu": {"utilization": 0.0, "memory_used_mb": 14.0, "memory_total_mb": 23034.0}}
{"timestamp": "2026-05-06T00:14:49.971067+00:00", "hostname": "frank-XPS-8960", "gpu_type": "NVIDIA L4", "gpu_count": 1, "cpu_percent": 0.0, "memory_percent": 17.5, "memory_used_mb": 5558.88671875, "memory_total_mb": 31740.1875, "gpu": {"utilization": 0.0, "memory_used_mb": 14.0, "memory_total_mb": 23034.0}}
{"timestamp": "2026-05-06T00:14:51.332566+00:00", "hostname": "frank-XPS-8960", "gpu_type": "NVIDIA L4", "gpu_count": 1, "cpu_percent": 0.1, "memory_percent": 17.5, "memory_used_mb": 5564.45703125, "memory_total_mb": 31740.1875, "gpu": {"utilization": 0.0, "memory_used_mb": 14.0, "memory_total_mb": 23034.0}}
{"timestamp": "2026-05-06T00:15:00.489292+00:00", "hostname": "frank-XPS-8960", "gpu_type": "NVIDIA L4", "gpu_count": 1, "cpu_percent": 0.1, "memory_percent": 17.5, "memory_used_mb": 5548.71875, "memory_total_mb": 31740.1875, "gpu": {"utilization": 0.0, "memory_used_mb": 14.0, "memory_total_mb": 23034.0}}
{"timestamp": "2026-05-06T00:15:01.849895+00:00", "hostname": "frank-XPS-8960", "gpu_type": "NVIDIA L4", "gpu_count": 1, "cpu_percent": 0.1, "memory_percent": 17.5, "memory_used_mb": 5558.9453125, "memory_total_mb": 31740.1875, "gpu": {"utilization": 0.0, "memory_used_mb": 14.0, "memory_total_mb": 23034.0}}
{"timestamp": "2026-05-06T00:15:11.006848+00:00", "hostname": "frank-XPS-8960", "gpu_type": "NVIDIA L4", "gpu_count": 1, "cpu_percent": 0.1, "memory_percent": 17.5, "memory_used_mb": 5550.50390625, "memory_total_mb": 31740.1875, "gpu": {"utilization": 0.0, "memory_used_mb": 14.0, "memory_total_mb": 23034.0}}
{"timestamp": "2026-05-06T00:15:12.368704+00:00", "hostname": "frank-XPS-8960", "gpu_type": "NVIDIA L4", "gpu_count": 1, "cpu_percent": 0.2, "memory_percent": 17.5, "memory_used_mb": 5551.54296875, "memory_total_mb": 31740.1875, "gpu": {"utilization": 0.0, "memory_used_mb": 14.0, "memory_total_mb": 23034.0}}
{"timestamp": "2026-05-06T00:15:21.523989+00:00", "hostname": "frank-XPS-8960", "gpu_type": "NVIDIA L4", "gpu_count": 1, "cpu_percent": 0.3, "memory_percent": 17.4, "memory_used_mb": 5535.14453125, "memory_total_mb": 31740.1875, "gpu": {"utilization": 0.0, "memory_used_mb": 14.0, "memory_total_mb": 23034.0}}
{"timestamp": "2026-05-06T00:15:22.885735+00:00", "hostname": "frank-XPS-8960", "gpu_type": "NVIDIA L4", "gpu_count": 1, "cpu_percent": 0.8, "memory_percent": 17.5, "memory_used_mb": 5543.359375, "memory_total_mb": 31740.1875, "gpu": {"utilization": 0.0, "memory_used_mb": 14.0, "memory_total_mb": 23034.0}}
{"timestamp": "2026-05-06T00:15:32.041484+00:00", "hostname": "frank-XPS-8960", "gpu_type": "NVIDIA L4", "gpu_count": 1, "cpu_percent": 0.1, "memory_percent": 17.5, "memory_used_mb": 5543.91015625, "memory_total_mb": 31740.1875, "gpu": {"utilization": 0.0, "memory_used_mb": 14.0, "memory_total_mb": 23034.0}}
{"timestamp": "2026-05-06T00:15:33.402760+00:00", "hostname": "frank-XPS-8960", "gpu_type": "NVIDIA L4", "gpu_count": 1, "cpu_percent": 0.1, "memory_percent": 17.5, "memory_used_mb": 5555.45703125, "memory_total_mb": 31740.1875, "gpu": {"utilization": 0.0, "memory_used_mb": 14.0, "memory_total_mb": 23034.0}}
{"timestamp": "2026-05-06T00:15:42.560633+00:00", "hostname": "frank-XPS-8960", "gpu_type": "NVIDIA L4", "gpu_count": 1, "cpu_percent": 0.3, "memory_percent": 17.5, "memory_used_mb": 5546.015625, "memory_total_mb": 31740.1875, "gpu": {"utilization": 0.0, "memory_used_mb": 14.0, "memory_total_mb": 23034.0}}
{"timestamp": "2026-05-06T00:15:43.919808+00:00", "hostname": "frank-XPS-8960", "gpu_type": "NVIDIA L4", "gpu_count": 1, "cpu_percent": 0.1, "memory_percent": 17.5, "memory_used_mb": 5544.79296875, "memory_total_mb": 31740.1875, "gpu": {"utilization": 0.0, "memory_used_mb": 14.0, "memory_total_mb": 23034.0}}
{"timestamp": "2026-05-06T00:15:53.077815+00:00", "hostname": "frank-XPS-8960", "gpu_type": "NVIDIA L4", "gpu_count": 1, "cpu_percent": 0.1, "memory_percent": 17.6, "memory_used_mb": 5571.8359375, "memory_total_mb": 31740.1875, "gpu": {"utilization": 0.0, "memory_used_mb": 14.0, "memory_total_mb": 23034.0}}
{"timestamp": "2026-05-06T00:15:54.436801+00:00", "hostname": "frank-XPS-8960", "gpu_type": "NVIDIA L4", "gpu_count": 1, "cpu_percent": 0.4, "memory_percent": 17.6, "memory_used_mb": 5571.6640625, "memory_total_mb": 31740.1875, "gpu": {"utilization": 0.0, "memory_used_mb": 14.0, "memory_total_mb": 23034.0}}
{"timestamp": "2026-05-06T00:16:03.594906+00:00", "hostname": "frank-XPS-8960", "gpu_type": "NVIDIA L4", "gpu_count": 1, "cpu_percent": 0.3, "memory_percent": 17.5, "memory_used_mb": 5558.09375, "memory_total_mb": 31740.1875, "gpu": {"utilization": 0.0, "memory_used_mb": 14.0, "memory_total_mb": 23034.0}}
{"timestamp": "2026-05-06T00:16:04.954665+00:00", "hostname": "frank-XPS-8960", "gpu_type": "NVIDIA L4", "gpu_count": 1, "cpu_percent": 0.2, "memory_percent": 17.5, "memory_used_mb": 5557.14453125, "memory_total_mb": 31740.1875, "gpu": {"utilization": 0.0, "memory_used_mb": 14.0, "memory_total_mb": 23034.0}}
{"timestamp": "2026-05-06T00:16:14.115342+00:00", "hostname": "frank-XPS-8960", "gpu_type": "NVIDIA L4", "gpu_count": 1, "cpu_percent": 0.7, "memory_percent": 17.6, "memory_used_mb": 5582.55078125, "memory_total_mb": 31740.1875, "gpu": {"utilization": 0.0, "memory_used_mb": 14.0, "memory_total_mb": 23034.0}}
{"timestamp": "2026-05-06T00:16:15.471328+00:00", "hostname": "frank-XPS-8960", "gpu_type": "NVIDIA L4", "gpu_count": 1, "cpu_percent": 0.0, "memory_percent": 17.6, "memory_used_mb": 5582.98046875, "memory_total_mb": 31740.1875, "gpu": {"utilization": 0.0, "memory_used_mb": 14.0, "memory_total_mb": 23034.0}}
{"timestamp": "2026-05-06T00:16:24.633207+00:00", "hostname": "frank-XPS-8960", "gpu_type": "NVIDIA L4", "gpu_count": 1, "cpu_percent": 0.5, "memory_percent": 17.6, "memory_used_mb": 5571.5546875, "memory_total_mb": 31740.1875, "gpu": {"utilization": 0.0, "memory_used_mb": 14.0, "memory_total_mb": 23034.0}}
{"timestamp": "2026-05-06T00:16:25.987996+00:00", "hostname": "frank-XPS-8960", "gpu_type": "NVIDIA L4", "gpu_count": 1, "cpu_percent": 0.8, "memory_percent": 17.6, "memory_used_mb": 5577.91796875, "memory_total_mb": 31740.1875, "gpu": {"utilization": 0.0, "memory_used_mb": 14.0, "memory_total_mb": 23034.0}}
{"timestamp": "2026-05-06T00:16:35.150874+00:00", "hostname": "frank-XPS-8960", "gpu_type": "NVIDIA L4", "gpu_count": 1, "cpu_percent": 0.2, "memory_percent": 17.5, "memory_used_mb": 5562.85546875, "memory_total_mb": 31740.1875, "gpu": {"utilization": 0.0, "memory_used_mb": 14.0, "memory_total_mb": 23034.0}}
{"timestamp": "2026-05-06T00:16:36.505716+00:00", "hostname": "frank-XPS-8960", "gpu_type": "NVIDIA L4", "gpu_count": 1, "cpu_percent": 0.1, "memory_percent": 17.6, "memory_used_mb": 5573.07421875, "memory_total_mb": 31740.1875, "gpu": {"utilization": 0.0, "memory_used_mb": 14.0, "memory_total_mb": 23034.0}}
{"timestamp": "2026-05-06T00:16:45.670983+00:00", "hostname": "frank-XPS-8960", "gpu_type": "NVIDIA L4", "gpu_count": 1, "cpu_percent": 3.9, "memory_percent": 19.9, "memory_used_mb": 6306.78125, "memory_total_mb": 31740.1875, "gpu": {"utilization": 0.0, "memory_used_mb": 242.0, "memory_total_mb": 23034.0}}
{"timestamp": "2026-05-06T00:16:47.025330+00:00", "hostname": "frank-XPS-8960", "gpu_type": "NVIDIA L4", "gpu_count": 1, "cpu_percent": 2.6, "memory_percent": 22.0, "memory_used_mb": 6976.2734375, "memory_total_mb": 31740.1875, "gpu": {"utilization": 1.0, "memory_used_mb": 22264.0, "memory_total_mb": 23034.0}}
{"timestamp": "2026-05-06T03:11:21.099671+00:00", "hostname": "frank-XPS-8960", "gpu_type": "NVIDIA L4", "gpu_count": 1, "cpu_percent": 0.7, "memory_percent": 17.5, "memory_used_mb": 5565.171875, "memory_total_mb": 31740.1875, "gpu": {"utilization": 0.0, "memory_used_mb": 14.0, "memory_total_mb": 23034.0}}
{"timestamp": "2026-05-06T03:11:24.854156+00:00", "hostname": "frank-XPS-8960", "gpu_type": "NVIDIA L4", "gpu_count": 1, "cpu_percent": 0.1, "memory_percent": 17.7, "memory_used_mb": 5620.01953125, "memory_total_mb": 31740.1875, "gpu": {"utilization": 0.0, "memory_used_mb": 14.0, "memory_total_mb": 23034.0}}
{"timestamp": "2026-05-06T03:11:31.618809+00:00", "hostname": "frank-XPS-8960", "gpu_type": "NVIDIA L4", "gpu_count": 1, "cpu_percent": 0.1, "memory_percent": 17.7, "memory_used_mb": 5605.5234375, "memory_total_mb": 31740.1875, "gpu": {"utilization": 0.0, "memory_used_mb": 14.0, "memory_total_mb": 23034.0}}
{"timestamp": "2026-05-06T03:11:35.374660+00:00", "hostname": "frank-XPS-8960", "gpu_type": "NVIDIA L4", "gpu_count": 1, "cpu_percent": 0.1, "memory_percent": 17.6, "memory_used_mb": 5587.83984375, "memory_total_mb": 31740.1875, "gpu": {"utilization": 0.0, "memory_used_mb": 14.0, "memory_total_mb": 23034.0}}
{"timestamp": "2026-05-06T03:11:42.136688+00:00", "hostname": "frank-XPS-8960", "gpu_type": "NVIDIA L4", "gpu_count": 1, "cpu_percent": 0.1, "memory_percent": 17.6, "memory_used_mb": 5578.640625, "memory_total_mb": 31740.1875, "gpu": {"utilization": 0.0, "memory_used_mb": 14.0, "memory_total_mb": 23034.0}}
{"timestamp": "2026-05-06T03:11:45.895672+00:00", "hostname": "frank-XPS-8960", "gpu_type": "NVIDIA L4", "gpu_count": 1, "cpu_percent": 0.6, "memory_percent": 17.7, "memory_used_mb": 5604.9765625, "memory_total_mb": 31740.1875, "gpu": {"utilization": 0.0, "memory_used_mb": 14.0, "memory_total_mb": 23034.0}}
{"timestamp": "2026-05-06T03:11:52.654929+00:00", "hostname": "frank-XPS-8960", "gpu_type": "NVIDIA L4", "gpu_count": 1, "cpu_percent": 0.6, "memory_percent": 17.6, "memory_used_mb": 5572.98046875, "memory_total_mb": 31740.1875, "gpu": {"utilization": 0.0, "memory_used_mb": 14.0, "memory_total_mb": 23034.0}}
{"timestamp": "2026-05-06T03:11:56.413719+00:00", "hostname": "frank-XPS-8960", "gpu_type": "NVIDIA L4", "gpu_count": 1, "cpu_percent": 0.2, "memory_percent": 17.5, "memory_used_mb": 5561.48046875, "memory_total_mb": 31740.1875, "gpu": {"utilization": 0.0, "memory_used_mb": 14.0, "memory_total_mb": 23034.0}}
{"timestamp": "2026-05-06T03:12:03.175089+00:00", "hostname": "frank-XPS-8960", "gpu_type": "NVIDIA L4", "gpu_count": 1, "cpu_percent": 0.3, "memory_percent": 17.5, "memory_used_mb": 5565.83984375, "memory_total_mb": 31740.1875, "gpu": {"utilization": 0.0, "memory_used_mb": 14.0, "memory_total_mb": 23034.0}}
{"timestamp": "2026-05-06T03:12:06.934445+00:00", "hostname": "frank-XPS-8960", "gpu_type": "NVIDIA L4", "gpu_count": 1, "cpu_percent": 0.1, "memory_percent": 17.6, "memory_used_mb": 5579.7578125, "memory_total_mb": 31740.1875, "gpu": {"utilization": 0.0, "memory_used_mb": 14.0, "memory_total_mb": 23034.0}}
{"timestamp": "2026-05-06T03:12:13.693656+00:00", "hostname": "frank-XPS-8960", "gpu_type": "NVIDIA L4", "gpu_count": 1, "cpu_percent": 0.4, "memory_percent": 17.6, "memory_used_mb": 5584.98046875, "memory_total_mb": 31740.1875, "gpu": {"utilization": 0.0, "memory_used_mb": 14.0, "memory_total_mb": 23034.0}}
{"timestamp": "2026-05-06T03:12:17.454598+00:00", "hostname": "frank-XPS-8960", "gpu_type": "NVIDIA L4", "gpu_count": 1, "cpu_percent": 0.1, "memory_percent": 17.6, "memory_used_mb": 5586.59375, "memory_total_mb": 31740.1875, "gpu": {"utilization": 0.0, "memory_used_mb": 14.0, "memory_total_mb": 23034.0}}
{"timestamp": "2026-05-06T03:12:24.212745+00:00", "hostname": "frank-XPS-8960", "gpu_type": "NVIDIA L4", "gpu_count": 1, "cpu_percent": 0.5, "memory_percent": 17.6, "memory_used_mb": 5588.1484375, "memory_total_mb": 31740.1875, "gpu": {"utilization": 0.0, "memory_used_mb": 14.0, "memory_total_mb": 23034.0}}
{"timestamp": "2026-05-06T03:12:27.971812+00:00", "hostname": "frank-XPS-8960", "gpu_type": "NVIDIA L4", "gpu_count": 1, "cpu_percent": 0.5, "memory_percent": 17.6, "memory_used_mb": 5587.8046875, "memory_total_mb": 31740.1875, "gpu": {"utilization": 0.0, "memory_used_mb": 14.0, "memory_total_mb": 23034.0}}
{"timestamp": "2026-05-06T03:12:34.730654+00:00", "hostname": "frank-XPS-8960", "gpu_type": "NVIDIA L4", "gpu_count": 1, "cpu_percent": 0.1, "memory_percent": 17.6, "memory_used_mb": 5584.2265625, "memory_total_mb": 31740.1875, "gpu": {"utilization": 0.0, "memory_used_mb": 14.0, "memory_total_mb": 23034.0}}
{"timestamp": "2026-05-06T03:12:38.489352+00:00", "hostname": "frank-XPS-8960", "gpu_type": "NVIDIA L4", "gpu_count": 1, "cpu_percent": 0.1, "memory_percent": 17.6, "memory_used_mb": 5589.73828125, "memory_total_mb": 31740.1875, "gpu": {"utilization": 0.0, "memory_used_mb": 14.0, "memory_total_mb": 23034.0}}
